ansys/grantami/dataflow_extensions/__init__.py
ansys/grantami/dataflow_extensions/_logger.py
ansys/grantami/dataflow_extensions/_mi_dataflow.py
ansys/grantami/dataflow_extensions/py.typed
ansys_grantami_dataflow_extensions-0.2.0.dist-info/LICENSE
ansys_grantami_dataflow_extensions-0.2.0.dist-info/METADATA
ansys_grantami_dataflow_extensions-0.2.0.dist-info/WHEEL
ansys_grantami_dataflow_extensions-0.2.0.dist-info/RECORD
