Metadata-Version: 2.3
Name: ansys-grantami-dataflow-extensions
Version: 0.2.0
Summary: Productivity package for use with Granta MI Dataflow.
License: MIT
Author: ANSYS, Inc.
Author-email: pyansys.core@ansys.com
Maintainer: ANSYS, Inc.
Maintainer-email: pyansys.core@ansys.com
Requires-Python: >=3.10,<4.0
Classifier: Development Status :: 5 - Production/Stable
Classifier: License :: OSI Approved :: MIT License
Classifier: Operating System :: Microsoft :: Windows
Classifier: Programming Language :: Python :: 3
Classifier: Programming Language :: Python :: 3.10
Classifier: Programming Language :: Python :: 3.11
Classifier: Programming Language :: Python :: 3.12
Classifier: Programming Language :: Python :: 3.13
Requires-Dist: ansys-openapi-common (>=2.3.0,<3.0.0)
Requires-Dist: requests (>=2.23,<3.0)
Requires-Dist: requests-negotiate-sspi (>=0.5.2,<0.6.0)
Project-URL: Documentation, https://dataflow-extensions.grantami.docs.pyansys.com
Project-URL: Repository, https://github.com/ansys/grantami-dataflow-extensions
